bb84_crypto/__init__.py
bb84_crypto/bb84.py
bb84_crypto-1.0.0.dist-info/LICENSE
bb84_crypto-1.0.0.dist-info/METADATA
bb84_crypto-1.0.0.dist-info/WHEEL
bb84_crypto-1.0.0.dist-info/top_level.txt
bb84_crypto-1.0.0.dist-info/RECORD
