Metadata-Version: 2.2
Name: bb84_crypto
Version: 1.0.0
Summary: A simple implementation of the BB84 quantum key distribution protocol.
Home-page: https://github.com/yourusername/bb84_crypto
Author: Amir
Author-email: ak2testspace@gmail.com
Classifier: Programming Language :: Python :: 3
Classifier: License :: OSI Approved :: MIT License
Classifier: Operating System :: OS Independent
Requires-Python: >=3.6
License-File: LICENSE
Requires-Dist: numpy
Dynamic: author
Dynamic: author-email
Dynamic: classifier
Dynamic: description
Dynamic: description-content-type
Dynamic: home-page
Dynamic: requires-dist
Dynamic: requires-python
Dynamic: summary
